main.py
ngiab_prep-0.0.2.dist-info/METADATA
ngiab_prep-0.0.2.dist-info/WHEEL
ngiab_prep-0.0.2.dist-info/entry_points.txt
ngiab_prep-0.0.2.dist-info/top_level.txt
ngiab_prep-0.0.2.dist-info/RECORD
