Metadata-Version: 2.4
Name: ngiab-prep
Version: 0.0.2
Summary: Graphical Tools for creating Next Gen Water model input data.
Author-email: Josh Cunningham <jcunningham8@ua.edu>
Project-URL: Homepage, https://github.com/CIROH-UA/NGIAB_data_preprocess
Project-URL: Issues, https://github.com/CIROH-UA/NGIAB_data_preprocess/issues
Classifier: Programming Language :: Python :: 3
Classifier: License :: OSI Approved :: MIT License
Classifier: Operating System :: OS Independent
Requires-Python: >=3.10
Requires-Dist: ngiab_data_preprocess
Provides-Extra: eval
Requires-Dist: ngiab_eval; extra == "eval"
Provides-Extra: plot
Requires-Dist: ngiab_eval[plot]; extra == "plot"
